{"ok": true, "results": [{"origin": "brightonandhove1010.org", "name": "harvey hill", "url": "http:\/\/www.harveyhill.co.uk", "country": "GB", "percent_reduction": null, "postcode": "bn2 1ws", "signed_up_datetime": "2011-01-03T11:34:37.097276", "type": "Businesses"}, {"origin": "1010", "name": "Center for innertruth", "url": "http:\/\/www.centerforinnertruth.nl", "country": "NL", "percent_reduction": null, "postcode": "1964jh", "signed_up_datetime": "2011-01-03T13:55:06.440308", "type": "Businesses"}, {"origin": "1010global.org\/uk\/join", "name": "Colwyn Bay Cricket Club", "url": "http:\/\/www.colwynbaycricketclub.co.uk", "country": "GB", "percent_reduction": null, "postcode": "LL28 4LR", "signed_up_datetime": "2011-01-03T14:09:34.060276", "type": "Clubs"}, {"origin": "1010", "name": "CAPAD, Cooperation des Association pour la Production Agricole et du Developpement.", "url": "http:\/\/capadc@yahoo.com", "country": "FR", "percent_reduction": null, "postcode": "BP 185 HT 8110", "signed_up_datetime": "2011-01-04T00:50:26.787488", "type": "Charities"}, {"origin": "1010", "name": "designtap", "url": "http:\/\/www.designtap.org", "country": "GB", "percent_reduction": null, "postcode": "N1 4NW", "signed_up_datetime": "2011-01-04T15:08:59.401626", "type": "Businesses"}, {"origin": "1010", "name": "Bournemouth and Poole College", "url": "http:\/\/thecollege.co.uk", "country": "GB", "percent_reduction": null, "postcode": "BH14 0LS", "signed_up_datetime": "2011-01-04T15:51:33.565387", "type": "Universities and colleges"}, {"origin": "1010", "name": "Atriv\u00e9", "url": "http:\/\/www.atrive.nl", "country": "NL", "percent_reduction": null, "postcode": "3994 DJ", "signed_up_datetime": "2011-01-05T11:12:29.387185", "type": "Businesses"}, {"origin": "1010", "name": "UPJV Jules Verne", "url": null, "country": "FR", "percent_reduction": null, "postcode": "80000", "signed_up_datetime": "2011-01-05T20:04:59.643059", "type": "Universities and colleges"}, {"origin": "1010", "name": "Les Guarrigues", "url": null, "country": "FR", "percent_reduction": null, "postcode": "13640", "signed_up_datetime": "2011-01-06T12:25:49.583484", "type": "Schools"}, {"origin": "1010global.org\/uk\/join", "name": "heat your home for less ltd", "url": "http:\/\/www.heatyourhomeforless.co.uk", "country": "GB", "percent_reduction": null, "postcode": "SO15 1HN", "signed_up_datetime": "2011-01-06T12:33:20.349480", "type": "Other organisations"}, {"origin": "1010", "name": "eruption", "url": "http:\/\/www.eruption.org.uk", "country": "GB", "percent_reduction": null, "postcode": "dn16 1tl", "signed_up_datetime": "2011-01-06T15:58:20.933286", "type": "Businesses"}, {"origin": "1010", "name": "C3", "url": null, "country": "FR", "percent_reduction": null, "postcode": "33600 PESSAC", "signed_up_datetime": "2011-01-07T08:57:41.069473", "type": "Universities and colleges"}, {"origin": "1010", "name": "Monkfish Events", "url": "http:\/\/www.monkfishevents.co.uk", "country": "GB", "percent_reduction": null, "postcode": "TW9 2PR", "signed_up_datetime": "2011-01-07T12:43:37.323084", "type": "Businesses"}, {"origin": "1010", "name": "Jewelrama.com", "url": "http:\/\/www.jewelrama.com", "country": "GB", "percent_reduction": null, "postcode": "CT12 6FA", "signed_up_datetime": "2011-01-07T15:32:24.869022", "type": "Businesses"}, {"origin": "1010nl.org", "name": "Mondiaal Centrum Maastricht", "url": "http:\/\/www.mondiaal-centrum.nl", "country": "NL", "percent_reduction": null, "postcode": "6211HT", "signed_up_datetime": "2011-01-08T13:22:33.525759", "type": "Other organisations"}, {"origin": "1010", "name": "CooLED, Inc", "url": "http:\/\/www.cooledinc.com", "country": "US", "percent_reduction": null, "postcode": "49685-0907", "signed_up_datetime": "2011-01-08T17:05:40.559540", "type": "Businesses"}, {"origin": "1010", "name": "Weymouth College", "url": "http:\/\/www.weymouth.ac.uk", "country": "GB", "percent_reduction": null, "postcode": "DT4 7LQ", "signed_up_datetime": "2011-01-10T14:58:08.142960", "type": "Universities and colleges"}, {"origin": "1010", "name": "Tarmac National Contracting", "url": "http:\/\/www.tarmac.co.uk", "country": "GB", "percent_reduction": null, "postcode": "DE55 2DS", "signed_up_datetime": "2011-01-10T16:38:04.521528", "type": "Businesses"}, {"origin": "1010", "name": "Familien Trondhjem", "url": null, "country": "DK", "percent_reduction": null, "postcode": "5270", "signed_up_datetime": "2011-01-10T21:22:39.782721", "type": "Other organisations"}, {"origin": "1010", "name": "Rivermead Construction Ltd", "url": "http:\/\/www.rivermeadconstruction.co.uk", "country": "GB", "percent_reduction": null, "postcode": "NG18 2RL", "signed_up_datetime": "2011-01-11T09:10:32.385706", "type": "Businesses"}, {"origin": "1010", "name": "Syndicat d'agglom\u00e9ration nouvelle de S\u00e9nart", "url": "http:\/\/www.senart.com", "country": "FR", "percent_reduction": null, "postcode": "77127", "signed_up_datetime": "2011-01-11T10:36:39.001861", "type": "Local government"}, {"origin": "1010", "name": "Komplement\u00e4rw\u00e4hrung", "url": "http:\/\/www.coinstatt.org", "country": "DE", "percent_reduction": null, "postcode": "58313", "signed_up_datetime": "2011-01-12T13:34:25.108881", "type": "Businesses"}, {"origin": "1010", "name": "investinlife", "url": "http:\/\/www.investinlife.de", "country": "DE", "percent_reduction": null, "postcode": "50674", "signed_up_datetime": "2011-01-12T15:52:57.929110", "type": "Businesses"}, {"origin": "1010global.org\/uk\/join", "name": "ashburton primary school", "url": "http:\/\/www.ashburton-primary.devon.sch.uk", "country": "GB", "percent_reduction": null, "postcode": "TQ13  7DB", "signed_up_datetime": "2011-01-13T10:50:40.595700", "type": "Schools"}, {"origin": "1010", "name": "Excellent World Foundation", "url": "http:\/\/www.excellentworldfoundation.co.uk", "country": "NG", "percent_reduction": null, "postcode": "47", "signed_up_datetime": "2011-01-13T16:30:22.413364", "type": "Health organisations"}, {"origin": "1010", "name": "Boule d'Energie", "url": "http:\/\/www.bouledenergie.com", "country": "FR", "percent_reduction": null, "postcode": "06160 Juan les Pins", "signed_up_datetime": "2011-01-14T09:41:04.012079", "type": "Businesses"}, {"origin": "1010nl.org", "name": "Vereniging van Keurslagers", "url": "http:\/\/www.keurslager.nl", "country": "NL", "percent_reduction": null, "postcode": "3833 LD", "signed_up_datetime": "2011-01-14T10:30:17.057982", "type": "Businesses"}, {"origin": "1010nl.org", "name": "VersPlatform Nederland", "url": "http:\/\/www.versplatformnederland.nl", "country": "NL", "percent_reduction": null, "postcode": "3833 LD", "signed_up_datetime": "2011-01-14T10:33:56.315403", "type": "Businesses"}, {"origin": "1010", "name": "animalmundi UG", "url": "http:\/\/www.animalmundi.com", "country": "DE", "percent_reduction": null, "postcode": "21272", "signed_up_datetime": "2011-01-14T11:08:40.662017", "type": "Schools"}, {"origin": "1010", "name": "River and Rowing Museum", "url": "http:\/\/www.rrm.co.uk", "country": "GB", "percent_reduction": null, "postcode": "RG9 1BF", "signed_up_datetime": "2011-01-14T11:12:39.019321", "type": "Other organisations"}, {"origin": "1010", "name": "Broad Street Mall", "url": "http:\/\/www.broadstreetmall.com", "country": "GB", "percent_reduction": null, "postcode": "RG1 7QE", "signed_up_datetime": "2011-01-14T12:38:09.229827", "type": "Businesses"}, {"origin": "1010", "name": "Projet C3", "url": "http:\/\/en cours de r\u00e9alisation", "country": "FR", "percent_reduction": null, "postcode": "33608 PESSAC", "signed_up_datetime": "2011-01-14T12:55:31.787650", "type": "Other organisations"}, {"origin": "1010", "name": "O2i Design Ltd", "url": "http:\/\/www.o2idesign.com", "country": "GB", "percent_reduction": null, "postcode": "TA10 9PD", "signed_up_datetime": "2011-01-14T12:59:43.438722", "type": "Businesses"}, {"origin": "1010", "name": "Conseil r\u00e9gional de Picardie", "url": "http:\/\/picardie.fr", "country": "FR", "percent_reduction": null, "postcode": "80026 Amiens cedex", "signed_up_datetime": "2011-01-15T10:48:12.542555", "type": "Local government"}, {"origin": "1010global.org\/uk\/join", "name": "Armadillo Hull", "url": "http:\/\/Armadillostorage.co.uk", "country": "GB", "percent_reduction": null, "postcode": "hu8 7jj", "signed_up_datetime": "2011-01-15T11:47:14.610221", "type": "Businesses"}, {"origin": "1010", "name": "adci", "url": "http:\/\/adci.fr", "country": "FR", "percent_reduction": null, "postcode": "51140", "signed_up_datetime": "2011-01-15T18:21:21.732247", "type": "Businesses"}, {"origin": "1010", "name": "Druantia", "url": "http:\/\/www.druantia.be", "country": "BE", "percent_reduction": null, "postcode": "2500", "signed_up_datetime": "2011-01-15T20:55:08.030624", "type": "Businesses"}, {"origin": "1010", "name": "Morges", "url": "http:\/\/\u00e9xfuhs\u00e9", "country": "FR", "percent_reduction": null, "postcode": "18000", "signed_up_datetime": "2011-01-16T14:20:28.629492", "type": "Schools"}, {"origin": "1010", "name": "RealFIT", "url": null, "country": "PT", "percent_reduction": null, "postcode": "2615-- 339", "signed_up_datetime": "2011-01-16T20:59:40.861626", "type": "Clubs"}, {"origin": "1010global.org\/uk\/join", "name": "Gogreen2 Marketing Ltd", "url": "http:\/\/www.gogreen2.com", "country": "GB", "percent_reduction": null, "postcode": "LE1 6JJ", "signed_up_datetime": "2011-01-17T10:03:42.007481", "type": "Businesses"}, {"origin": "1010", "name": "Aboh-Ngoh Community Development  Organization", "url": null, "country": "CM", "percent_reduction": null, "postcode": "535 Buea", "signed_up_datetime": "2011-01-17T12:33:23.310293", "type": "Other organisations"}, {"origin": "1010global.org\/uk\/join", "name": "Luckings Transport", "url": "http:\/\/www.luckings.co.uk", "country": "GB", "percent_reduction": null, "postcode": "TW8 9JJ", "signed_up_datetime": "2011-01-17T14:54:39.423218", "type": "Businesses"}, {"origin": "1010global.org\/uk\/join", "name": "Friends of the River kelvin", "url": "http:\/\/www.fork.org.uk", "country": "GB", "percent_reduction": null, "postcode": "G12 0DS", "signed_up_datetime": "2011-01-18T16:05:04.360000", "type": "Charities"}, {"origin": "1010global.org\/uk\/join", "name": "Firesnake", "url": "http:\/\/www.firesnake.com", "country": "GB", "percent_reduction": null, "postcode": "OX16 9NH", "signed_up_datetime": "2011-01-18T21:38:56.469105", "type": "Businesses"}, {"origin": "1010", "name": "Ysgol Gynradd Llandegfan", "url": null, "country": "GB", "percent_reduction": null, "postcode": "LL59 5UW", "signed_up_datetime": "2011-01-19T14:48:42.631595", "type": "Schools"}, {"origin": "1010", "name": "Literary Kitchen Ltd", "url": "http:\/\/literarykitchen.co.uk", "country": "GB", "percent_reduction": null, "postcode": "SE15 4BW", "signed_up_datetime": "2011-01-19T22:06:49.622553", "type": "Businesses"}, {"origin": "1010", "name": "THR (Consulting) Ltd", "url": "http:\/\/www.psychometrictests.org.uk", "country": "GB", "percent_reduction": null, "postcode": "RH17 5BD", "signed_up_datetime": "2011-01-20T09:17:32.317938", "type": "Businesses"}, {"origin": "1010", "name": "o2", "url": "http:\/\/www.o2.co.uk", "country": "GB", "percent_reduction": null, "postcode": "SL1 4DX", "signed_up_datetime": "2011-01-20T17:56:27.331133", "type": "Businesses"}, {"origin": "1010", "name": "Get-Eco", "url": "http:\/\/www.get-eco.co.uk", "country": "GB", "percent_reduction": null, "postcode": "GL10 3SX", "signed_up_datetime": "2011-01-21T11:16:45.061566", "type": "Businesses"}, {"origin": "1010", "name": "Collectif Senegalais des Africaines pour la Promotion de l'Education Relative a l'Environnement - COSAPERE", "url": null, "country": "SN", "percent_reduction": null, "postcode": "15022", "signed_up_datetime": "2011-01-21T12:10:47.721375", "type": "Businesses"}, {"origin": "1010", "name": "Be My Planet Ltd", "url": "http:\/\/www.bemyplanet.org", "country": "GB", "percent_reduction": null, "postcode": "LE2 2HE", "signed_up_datetime": "2011-01-21T16:03:57.464023", "type": "Businesses"}, {"origin": "1010", "name": "Tidy Planet Ltd", "url": "http:\/\/www.tidyplanet.co.uk", "country": "GB", "percent_reduction": null, "postcode": "SK10 2BN", "signed_up_datetime": "2011-01-22T12:21:51.683310", "type": "Businesses"}, {"origin": "1010", "name": "iTAN", "url": "http:\/\/skolestart.nu", "country": "DK", "percent_reduction": null, "postcode": "2791 Drag\u00f8r", "signed_up_datetime": "2011-01-23T08:30:06.941345", "type": "Businesses"}, {"origin": "1010", "name": "Redemption Research for Health and Educational Development Society(RRHEDS)", "url": "http:\/\/www.rrheds.org", "country": "IN", "percent_reduction": null, "postcode": "522616", "signed_up_datetime": "2011-01-23T10:44:35.480835", "type": "Charities"}, {"origin": "1010", "name": "far", "url": "http:\/\/galmim", "country": "FR", "percent_reduction": null, "postcode": "80001", "signed_up_datetime": "2011-01-23T10:49:35.268655", "type": "Student organisations"}, {"origin": "1010", "name": "far", "url": "http:\/\/maroc", "country": "FR", "percent_reduction": null, "postcode": "80001", "signed_up_datetime": "2011-01-23T10:52:11.291880", "type": "Student organisations"}, {"origin": "1010", "name": "The Great British Tea Party", "url": "http:\/\/www.thegreatbritishteaparty.co.uk", "country": "GB", "percent_reduction": null, "postcode": "TA2 6HX", "signed_up_datetime": "2011-01-23T11:47:47.581807", "type": "Businesses"}, {"origin": "1010", "name": "\u00e9cole priv\u00e9e andresena", "url": null, "country": "FR", "percent_reduction": null, "postcode": "103", "signed_up_datetime": "2011-01-23T14:45:34.286672", "type": "Schools"}, {"origin": "1010", "name": "Primeprox Security Services", "url": "http:\/\/www.primeprox.com", "country": "GB", "percent_reduction": null, "postcode": "CR0 1QE", "signed_up_datetime": "2011-01-23T15:16:47.045155", "type": "Businesses"}, {"origin": "1010", "name": "NVA", "url": "http:\/\/www.nva.org.uk", "country": "GB", "percent_reduction": null, "postcode": "G3 7NR", "signed_up_datetime": "2011-01-23T21:45:40.797953", "type": "Charities"}, {"origin": "1010", "name": "Wynter Road Community Group", "url": null, "country": "GB", "percent_reduction": null, "postcode": "SO18 6NY", "signed_up_datetime": "2011-01-24T11:43:41.856566", "type": "Other organisations"}, {"origin": "1010", "name": "Universit\u00e9 Lille", "url": null, "country": "FR", "percent_reduction": null, "postcode": "59000", "signed_up_datetime": "2011-01-24T14:54:30.971977", "type": "Universities and colleges"}, {"origin": "1010", "name": "Marea", "url": "http:\/\/mareadiving.com", "country": "FR", "percent_reduction": null, "postcode": "83130 LA GARDE", "signed_up_datetime": "2011-01-24T17:10:11.159377", "type": "Businesses"}, {"origin": "1010", "name": "INICIATIVAVERDS", "url": "http:\/\/www.iniciativaverds.org", "country": "ES", "percent_reduction": null, "postcode": "07001", "signed_up_datetime": "2011-01-24T19:39:29.787898", "type": "Other organisations"}, {"origin": "1010", "name": "Belswains Primary School", "url": "http:\/\/www.belswains.herts.sch.uk", "country": "GB", "percent_reduction": null, "postcode": "HP3 9QJ", "signed_up_datetime": "2011-01-25T09:32:51.333429", "type": "Schools"}, {"origin": "1010", "name": "CarbonRewind", "url": "http:\/\/www.carbonrewind.com", "country": "GB", "percent_reduction": null, "postcode": "SW", "signed_up_datetime": "2011-01-25T11:52:43.773310", "type": "Businesses"}, {"origin": "1010", "name": "UKQMS LTD", "url": "http:\/\/www.ukqms.com", "country": "GB", "percent_reduction": null, "postcode": "WR3 8QT", "signed_up_datetime": "2011-01-25T13:20:53.888444", "type": "Businesses"}, {"origin": "1010finland.fi", "name": "Omaoma Oy \/ Kuinoma.fi", "url": "http:\/\/www.kuinoma.fi", "country": "FI", "percent_reduction": null, "postcode": "00530", "signed_up_datetime": "2011-01-25T13:51:02.113008", "type": "Businesses"}, {"origin": "1010", "name": "Central Training UK LTD", "url": "http:\/\/www.centraltraininggroup.org", "country": "GB", "percent_reduction": null, "postcode": "wa10 2jb", "signed_up_datetime": "2011-01-25T15:16:31.255348", "type": "Businesses"}, {"origin": "1010", "name": "Abbey Windows (Thames Valley) Ltd", "url": "http:\/\/www.abbeywindows.co.uk", "country": "GB", "percent_reduction": null, "postcode": "RG1 8HS", "signed_up_datetime": "2011-01-25T18:04:08.701288", "type": "Businesses"}, {"origin": "1010", "name": "lifef forneedy children", "url": "http:\/\/n \/a", "country": "KE", "percent_reduction": null, "postcode": "30500", "signed_up_datetime": "2011-01-25T19:28:44.105226", "type": "Schools"}, {"origin": "1010global.org\/uk\/join", "name": "Heatshot Limited", "url": "http:\/\/www.heatshot.co.uk", "country": "GB", "percent_reduction": null, "postcode": "Y08 8HF", "signed_up_datetime": "2011-01-26T11:47:56.811203", "type": "Businesses"}, {"origin": "1010", "name": "OXEA", "url": "http:\/\/www.oxeaconseil.Com", "country": "FR", "percent_reduction": null, "postcode": "75017", "signed_up_datetime": "2011-01-26T13:25:52.281082", "type": "Businesses"}, {"origin": "1010", "name": "Lockside", "url": "http:\/\/www.locksidelounge.com", "country": "GB", "percent_reduction": null, "postcode": "NW1 8AF", "signed_up_datetime": "2011-01-26T14:35:11.126542", "type": "Other organisations"}, {"origin": "1010", "name": "Little White Alice", "url": "http:\/\/www.littlewhitealice.co.uk", "country": "GB", "percent_reduction": null, "postcode": "TR16 6PL", "signed_up_datetime": "2011-01-27T10:28:42.625635", "type": "Businesses"}, {"origin": "1010global.org\/uk\/join", "name": "Ligna", "url": null, "country": "GB", "percent_reduction": null, "postcode": "B18 6NF", "signed_up_datetime": "2011-01-27T12:06:37.804620", "type": "Businesses"}, {"origin": "1010", "name": "juanktriana1967", "url": "http:\/\/www.myebook.com\/juanktriana1967", "country": "CO", "percent_reduction": null, "postcode": "763041", "signed_up_datetime": "2011-01-27T19:46:44.368489", "type": "Other organisations"}, {"origin": "1010", "name": "Philips Nederland", "url": "http:\/\/www.Philips.nl", "country": "NL", "percent_reduction": null, "postcode": "5621 JG Eindhoven", "signed_up_datetime": "2011-01-28T12:30:39.736789", "type": "Businesses"}, {"origin": "1010", "name": "Hartong", "url": "http:\/\/Hartong.nl", "country": "NL", "percent_reduction": null, "postcode": "1216 BW", "signed_up_datetime": "2011-01-28T14:29:44.527446", "type": "Businesses"}, {"origin": "1010", "name": "Adverpro.co.uk", "url": "http:\/\/www.adverpro.co.uk", "country": "GB", "percent_reduction": null, "postcode": "BL1 2BZ", "signed_up_datetime": "2011-01-29T00:37:12.416861", "type": "Businesses"}, {"origin": "1010", "name": "CDP", "url": "http:\/\/www.cdproject.net", "country": "GB", "percent_reduction": null, "postcode": "EC1R 0NE", "signed_up_datetime": "2011-01-29T10:46:36.560127", "type": "Businesses"}, {"origin": "1010", "name": "Trans Sustainability Global", "url": "http:\/\/transsustain.com", "country": "US", "percent_reduction": null, "postcode": "28105", "signed_up_datetime": "2011-01-29T19:16:18.752591", "type": "Businesses"}, {"origin": "1010", "name": "Bureau de l'education a l'evironnement", "url": null, "country": "FR", "percent_reduction": null, "postcode": "17121", "signed_up_datetime": "2011-01-30T02:28:56.080203", "type": "Other organisations"}, {"origin": "1010", "name": "Lookotels", "url": "http:\/\/www.lookotels.com", "country": "ES", "percent_reduction": null, "postcode": "20043", "signed_up_datetime": "2011-01-30T09:52:12.719552", "type": "Businesses"}, {"origin": "1010", "name": "Priorit\u00e9 Environnement", "url": null, "country": "FR", "percent_reduction": null, "postcode": "891", "signed_up_datetime": "2011-01-31T12:10:04.357049", "type": "Student organisations"}, {"origin": "1010", "name": "Vegware", "url": "http:\/\/www.vegware.com", "country": "GB", "percent_reduction": null, "postcode": "EH11 1HS", "signed_up_datetime": "2011-01-31T14:22:17.191702", "type": "Businesses"}, {"origin": "brightonandhove1010.org", "name": "Pestalozzi Internacional Village", "url": "http:\/\/www.pestalozzi.org.uk", "country": "GB", "percent_reduction": null, "postcode": "TN33 OUF", "signed_up_datetime": "2011-01-31T17:32:22.517129", "type": "Businesses"}, {"origin": "1010", "name": "Verde Heating Solutions Ltd", "url": "http:\/\/www.verdeheatingsolutions.co.uk", "country": "GB", "percent_reduction": null, "postcode": "SK67JB", "signed_up_datetime": "2011-02-01T08:32:14.440042", "type": "Businesses"}, {"origin": "1010", "name": "LolliBop", "url": "http:\/\/www.lollibopfestival.com", "country": "GB", "percent_reduction": null, "postcode": "N17 9NF", "signed_up_datetime": "2011-02-02T13:17:57.070026", "type": "Businesses"}, {"origin": "1010", "name": "Ecoserveis", "url": "http:\/\/www.ecoserveis.net", "country": "ES", "percent_reduction": null, "postcode": "08002", "signed_up_datetime": "2011-02-03T09:16:11.310135", "type": "Clubs"}, {"origin": "1010", "name": "Global Partners Services", "url": "http:\/\/www.gps-montage.fr", "country": "FR", "percent_reduction": null, "postcode": "72190", "signed_up_datetime": "2011-02-03T15:54:41.570678", "type": "Businesses"}, {"origin": "1010", "name": "Vifor Pharma UK Limited", "url": "http:\/\/www.viforpharma.co.uk", "country": "GB", "percent_reduction": null, "postcode": "GU19 5PJ", "signed_up_datetime": "2011-02-03T16:55:36.596738", "type": "Businesses"}, {"origin": "1010", "name": "oluft.com", "url": "http:\/\/www.oluft.com", "country": "DE", "percent_reduction": null, "postcode": "20146", "signed_up_datetime": "2011-02-03T19:14:16.824634", "type": "Businesses"}, {"origin": "1010", "name": "Internwise.co.uk", "url": "http:\/\/www.internwise.co.uk", "country": "GB", "percent_reduction": null, "postcode": "N6 5HN", "signed_up_datetime": "2011-02-03T23:49:00.151574", "type": "Businesses"}, {"origin": "1010", "name": "ATR Design Group", "url": "http:\/\/www.atrdesign.com", "country": "GB", "percent_reduction": null, "postcode": "EH7 6JA", "signed_up_datetime": "2011-02-05T16:22:30.428980", "type": "Businesses"}, {"origin": "1010", "name": "zenith university college", "url": null, "country": "GH", "percent_reduction": null, "postcode": "hp 276 ho, v\/r", "signed_up_datetime": "2011-02-06T00:31:52.968925", "type": "Universities and colleges"}, {"origin": "1010", "name": "Solve Naturally", "url": "http:\/\/www.solvenaturally.com", "country": "BE", "percent_reduction": null, "postcode": "2950", "signed_up_datetime": "2011-02-06T09:30:15.962229", "type": "Health organisations"}, {"origin": "1010", "name": "STU78", "url": null, "country": "TH", "percent_reduction": null, "postcode": "10310", "signed_up_datetime": "2011-02-06T16:40:18.260547", "type": "Universities and colleges"}, {"origin": "1010", "name": "The Good Life For All", "url": "http:\/\/www.thegoodlifeforall.com", "country": "GB", "percent_reduction": null, "postcode": "BN1 3AN", "signed_up_datetime": "2011-02-06T18:41:13.904235", "type": "Charities"}, {"origin": "1010", "name": "Bonjour TIC", "url": "http:\/\/www.bonjour-tic.com", "country": "FR", "percent_reduction": null, "postcode": "31400", "signed_up_datetime": "2011-02-07T04:31:53.987486", "type": "Businesses"}, {"origin": "1010", "name": "Microsoft Danmark", "url": "http:\/\/www.microsoft.dk\/groen", "country": "DK", "percent_reduction": null, "postcode": "2900", "signed_up_datetime": "2011-02-07T08:51:16.335288", "type": "Businesses"}, {"origin": "1010", "name": "Zinc Enterprises", "url": "http:\/\/www.zincarts.org.uk", "country": "GB", "percent_reduction": null, "postcode": "CM5 0AD", "signed_up_datetime": "2011-02-07T14:59:29.530350", "type": "Charities"}, {"origin": "1010", "name": "SHAMAR CHILDREN SCHOOL", "url": "http:\/\/NONE", "country": "NG", "percent_reduction": null, "postcode": "234", "signed_up_datetime": "2011-02-07T20:40:02.479163", "type": "Schools"}, {"origin": "1010global.org\/uk\/join", "name": "SHAMAR SCHOOL", "url": null, "country": "GB", "percent_reduction": null, "postcode": "234", "signed_up_datetime": "2011-02-07T20:58:09.844656", "type": "Businesses"}, {"origin": "1010", "name": "Exled", "url": "http:\/\/www.exled.co.uk", "country": "GB", "percent_reduction": null, "postcode": "GL5 2BU", "signed_up_datetime": "2011-02-08T10:30:18.629925", "type": "Businesses"}, {"origin": "1010", "name": "SavaSocket.com", "url": "http:\/\/savasocket.com", "country": "GB", "percent_reduction": null, "postcode": "LS17 6HZ", "signed_up_datetime": "2011-02-08T12:12:00.840546", "type": "Other organisations"}, {"origin": "1010finland.fi", "name": "GreenRiders", "url": "http:\/\/www.greenriders.com", "country": "FI", "percent_reduction": null, "postcode": "00120 HELSINKI", "signed_up_datetime": "2011-02-09T09:20:29.428137", "type": "Businesses"}, {"origin": "1010", "name": "SMD ltd", "url": "http:\/\/www.smdltd.co.uk", "country": "GB", "percent_reduction": null, "postcode": "BH12 4PY", "signed_up_datetime": "2011-02-09T11:16:37.015716", "type": "Businesses"}, {"origin": "1010", "name": "lets-service ltd", "url": "http:\/\/www.lets-service.com", "country": "GB", "percent_reduction": null, "postcode": "TW11 0BN", "signed_up_datetime": "2011-02-09T18:26:16.880000", "type": "Businesses"}, {"origin": "1010", "name": "African Communities Empowerment", "url": "http:\/\/www.africacome.org", "country": "UG", "percent_reduction": null, "postcode": "256", "signed_up_datetime": "2011-02-09T21:50:32.096150", "type": "Charities"}, {"origin": "1010", "name": "www.enarmonion.gr", "url": "http:\/\/eco-aegina.blogspot.com\/", "country": "GR", "percent_reduction": null, "postcode": "AEGINA", "signed_up_datetime": "2011-02-10T04:39:12.405150", "type": "Local government"}, {"origin": "1010global.org\/uk\/join", "name": "University of Bristol, Examinations Office", "url": null, "country": "GB", "percent_reduction": null, "postcode": "BS8 1TH", "signed_up_datetime": "2011-02-10T11:40:49.524228", "type": "Universities and colleges"}, {"origin": "1010", "name": "Malvern House", "url": "http:\/\/www.malvernhouse.com", "country": "GB", "percent_reduction": null, "postcode": "WC2E 8HR", "signed_up_datetime": "2011-02-10T15:08:07.781307", "type": "Businesses"}, {"origin": "1010", "name": "SWIIS Foster Care Newcastle", "url": "http:\/\/www.swiisfostercare.com\/index.asp", "country": "GB", "percent_reduction": null, "postcode": "NE3 5NA", "signed_up_datetime": "2011-02-10T15:13:16.544536", "type": "Businesses"}, {"origin": "1010", "name": "Brake the Cycle", "url": "http:\/\/www.brakethecycle.org.uk", "country": "GB", "percent_reduction": null, "postcode": "SE11 5PH", "signed_up_datetime": "2011-02-10T16:52:57.645138", "type": "Charities"}, {"origin": "1010", "name": "Lewis School of English", "url": "http:\/\/www.lewis-school.co.uk", "country": "GB", "percent_reduction": null, "postcode": "SO14 1LL", "signed_up_datetime": "2011-02-10T17:04:19.522501", "type": "Businesses"}, {"origin": "1010", "name": "JVE Niger", "url": "http:\/\/www.ong-jve.org", "country": "FR", "percent_reduction": null, "postcode": "11944", "signed_up_datetime": "2011-02-10T17:25:30.892015", "type": "Clubs"}, {"origin": "1010", "name": "Naturkostfachgesch\u00e4ft R\u00fcbe", "url": "http:\/\/www.ruebe-reichenbach.de", "country": "DE", "percent_reduction": null, "postcode": "73262 Reichenbach \/ Fils", "signed_up_datetime": "2011-02-10T22:30:26.912200", "type": "Businesses"}, {"origin": "1010nl.org", "name": "wiershoeck natuurvoeding", "url": "http:\/\/www.dewiershoeck.nl", "country": "NL", "percent_reduction": null, "postcode": "9737 ad", "signed_up_datetime": "2011-02-13T15:47:34.270225", "type": "Businesses"}, {"origin": "1010", "name": "Saint Michael's College", "url": "http:\/\/www.st-michaels.uk.com", "country": "GB", "percent_reduction": null, "postcode": "WR15 8PH", "signed_up_datetime": "2011-02-13T16:49:13.688316", "type": "Schools"}, {"origin": "1010", "name": "MADAGASCAR NATIONAL PARKS", "url": "http:\/\/www.parcs-madagascar.com", "country": "FR", "percent_reduction": null, "postcode": "103", "signed_up_datetime": "2011-02-14T10:55:11.982769", "type": "Businesses"}, {"origin": "1010", "name": "IH Aberdeen Ltd", "url": "http:\/\/ihaberdeen.com", "country": "GB", "percent_reduction": null, "postcode": "AB10 1JJ", "signed_up_datetime": "2011-02-14T11:25:26.079570", "type": "Other organisations"}, {"origin": "1010", "name": "Socioverde", "url": "http:\/\/www.socioverde.com", "country": "AR", "percent_reduction": null, "postcode": "1204", "signed_up_datetime": "2011-02-14T18:13:58.701025", "type": "Businesses"}, {"origin": "1010", "name": "Rural Route Video", "url": null, "country": "US", "percent_reduction": null, "postcode": "81137-0640", "signed_up_datetime": "2011-02-15T04:51:32.061562", "type": "Businesses"}, {"origin": "1010", "name": "British Embassy Dushanbe", "url": "http:\/\/ukintajikistan@fco.gov.uk", "country": "GB", "percent_reduction": null, "postcode": "HA4 6EP", "signed_up_datetime": "2011-02-15T15:59:40.725386", "type": "Other organisations"}, {"origin": "1010global.org\/uk\/join", "name": "British Study Centres School of English", "url": "http:\/\/www.british-study.com", "country": "GB", "percent_reduction": null, "postcode": "OX1 3AE", "signed_up_datetime": "2011-02-15T16:42:30.869977", "type": "Other organisations"}, {"origin": "1010global.org\/uk\/join", "name": "Toppers", "url": "http:\/\/www.toppersbuild.co.uk", "country": "GB", "percent_reduction": null, "postcode": "SW18 3NN", "signed_up_datetime": "2011-02-15T17:26:14.064355", "type": "Businesses"}, {"origin": "1010", "name": "Step Ahead Services", "url": "http:\/\/www.step-a-head.co.uk", "country": "GB", "percent_reduction": null, "postcode": "CR7 7EQ", "signed_up_datetime": "2011-02-15T23:57:21.595416", "type": "Businesses"}, {"origin": "1010", "name": "Greenworkforce London Handyman", "url": "http:\/\/www.greenworkforce.co.uk", "country": "GB", "percent_reduction": null, "postcode": "EC1V 9AU", "signed_up_datetime": "2011-02-16T00:14:30.660729", "type": "Businesses"}, {"origin": "1010finland.fi", "name": "A to B Finland Oy ( A2B )", "url": "http:\/\/www.a2b.fi", "country": "FI", "percent_reduction": null, "postcode": "00510 Helsinki", "signed_up_datetime": "2011-02-16T08:49:51.001181", "type": "Businesses"}, {"origin": "1010", "name": "De Lichtdrukkerij ReproService", "url": "http:\/\/www.delichtdrukkerij.com", "country": "NL", "percent_reduction": null, "postcode": "1689 AD  Zwaag", "signed_up_datetime": "2011-02-16T13:17:37.629282", "type": "Businesses"}, {"origin": "1010", "name": "Forma1", "url": "http:\/\/www.forma1.com.ar", "country": "AR", "percent_reduction": null, "postcode": "1204", "signed_up_datetime": "2011-02-16T19:56:59.059613", "type": "Businesses"}, {"origin": "1010nl.org", "name": "Bakker Bodemonderzoek BV", "url": "http:\/\/www.bakkerbodemonderzoek.nl", "country": "NL", "percent_reduction": null, "postcode": "1969 NH", "signed_up_datetime": "2011-02-17T07:15:49.509592", "type": "Businesses"}, {"origin": "brightonandhove1010.org", "name": "Portslade Health Centre Medical Practice", "url": "http:\/\/www.portsladehealthcentre.co.uk", "country": "GB", "percent_reduction": null, "postcode": "BN41 1LX", "signed_up_datetime": "2011-02-17T08:50:33.764835", "type": "Businesses"}, {"origin": "1010", "name": "Geria Sostenibilidad", "url": "http:\/\/www.geriasostenibilidad.com", "country": "ES", "percent_reduction": null, "postcode": "38002", "signed_up_datetime": "2011-02-18T10:14:30.243103", "type": "Businesses"}, {"origin": "1010nl.org", "name": "Voord\u00e9licht B.V.", "url": "http:\/\/www.voordelicht.nl", "country": "NL", "percent_reduction": null, "postcode": "3059XT", "signed_up_datetime": "2011-02-18T21:44:33.086665", "type": "Businesses"}, {"origin": "1010", "name": "University Centre Cesar Ritz", "url": "http:\/\/www.ritz.edu", "country": "GB", "percent_reduction": null, "postcode": "3900", "signed_up_datetime": "2011-02-19T00:38:37.512773", "type": "Universities and colleges"}, {"origin": "1010", "name": "Hyport Solu\u00e7\u00f5es Globais, SA", "url": "http:\/\/www.hyport.pt", "country": "PT", "percent_reduction": null, "postcode": "2890-182", "signed_up_datetime": "2011-02-19T19:10:25.733433", "type": "Businesses"}, {"origin": "1010nl.org", "name": "HotelsAhead BV", "url": "http:\/\/www.hotelsahead.com", "country": "NL", "percent_reduction": null, "postcode": "1483AD", "signed_up_datetime": "2011-02-20T06:00:43.981143", "type": "Businesses"}, {"origin": "1010", "name": "CO2NEUTRAL", "url": "http:\/\/www.co2.cl", "country": "CL", "percent_reduction": null, "postcode": "0000", "signed_up_datetime": "2011-02-20T20:49:40.196024", "type": "Businesses"}, {"origin": "1010", "name": "PlanMatrix Strategy", "url": "http:\/\/www.planmatrix.net", "country": "ZA", "percent_reduction": null, "postcode": "1401", "signed_up_datetime": "2011-02-21T05:34:29.227101", "type": "Businesses"}, {"origin": "1010", "name": "Sydney Theatre Company", "url": "http:\/\/www.sydneytheatre.com.au", "country": "AU", "percent_reduction": null, "postcode": "2000", "signed_up_datetime": "2011-02-21T08:23:41.300599", "type": "Businesses"}, {"origin": "1010", "name": "Xyone", "url": "http:\/\/www.xyone.co.uk", "country": "GB", "percent_reduction": null, "postcode": "M50 3UB", "signed_up_datetime": "2011-02-21T10:38:01.451078", "type": "Businesses"}, {"origin": "1010", "name": "Barnes Design", "url": "http:\/\/www.barnes-design.com", "country": "GB", "percent_reduction": null, "postcode": "SW11 2JD", "signed_up_datetime": "2011-02-21T17:33:52.036333", "type": "Businesses"}, {"origin": "1010", "name": "CreativeWork!", "url": "http:\/\/www.creativeworkdesign.co.uk", "country": "GB", "percent_reduction": null, "postcode": "NE30 4LY", "signed_up_datetime": "2011-02-22T12:30:35.106485", "type": "Businesses"}, {"origin": "1010", "name": "Planete Equalia", "url": "http:\/\/www.planete-equalia.fr", "country": "FR", "percent_reduction": null, "postcode": "92 110", "signed_up_datetime": "2011-02-22T14:49:41.720702", "type": "Businesses"}, {"origin": "1010", "name": "Kathmandu University", "url": "http:\/\/www.ku.edu.np", "country": "NP", "percent_reduction": null, "postcode": "44614", "signed_up_datetime": "2011-02-23T02:38:37.857585", "type": "Universities and colleges"}, {"origin": "1010", "name": "Wycombe Environment Centre", "url": "http:\/\/being updated.", "country": "GB", "percent_reduction": null, "postcode": "HP13 5HR", "signed_up_datetime": "2011-02-23T10:21:44.739134", "type": "Other organisations"}, {"origin": "1010", "name": "Age UK Nottingham and Nottinghamshire", "url": "http:\/\/www.ageuknotts.org.uk", "country": "GB", "percent_reduction": null, "postcode": "NG1 4FQ", "signed_up_datetime": "2011-02-23T11:30:20.918366", "type": "Charities"}, {"origin": "1010", "name": "green space", "url": null, "country": "IE", "percent_reduction": null, "postcode": "Co. Dublin", "signed_up_datetime": "2011-02-23T15:20:30.753124", "type": "Charities"}, {"origin": "1010", "name": "NSO", "url": null, "country": "GB", "percent_reduction": null, "postcode": "w12", "signed_up_datetime": "2011-02-23T15:29:18.791543", "type": "Businesses"}, {"origin": "1010", "name": "British High Commission, Dhaka", "url": "http:\/\/ukinbangladesh.fco.gov.uk", "country": "GB", "percent_reduction": null, "postcode": "SW1A 2AH", "signed_up_datetime": "2011-02-24T04:04:55.634622", "type": "Other organisations"}, {"origin": "1010", "name": "bil invest", "url": "http:\/\/www.bil-invest.com", "country": "GB", "percent_reduction": null, "postcode": "48009", "signed_up_datetime": "2011-02-24T10:53:46.789527", "type": "Businesses"}, {"origin": "1010", "name": "Herbcrafte", "url": "http:\/\/Not up yet", "country": "IE", "percent_reduction": null, "postcode": "None", "signed_up_datetime": "2011-02-24T12:18:52.010420", "type": "Businesses"}, {"origin": "1010", "name": "Ecowizer", "url": "http:\/\/www.ecowizer.com", "country": "HU", "percent_reduction": null, "postcode": "1054", "signed_up_datetime": "2011-02-25T12:59:48.629902", "type": "Businesses"}, {"origin": "1010", "name": "Global Freight Solutions", "url": "http:\/\/www.justshoutgfs.com", "country": "GB", "percent_reduction": null, "postcode": "RH14 9SJ", "signed_up_datetime": "2011-02-25T15:09:59.866917", "type": "Businesses"}, {"origin": "1010", "name": "none", "url": null, "country": "US", "percent_reduction": null, "postcode": "95301", "signed_up_datetime": "2011-02-26T04:24:46.555511", "type": "Universities and colleges"}, {"origin": "1010", "name": "Rose Theatre", "url": "http:\/\/www.rosetheatrekingston.org", "country": "GB", "percent_reduction": null, "postcode": "KT1 1HL", "signed_up_datetime": "2011-02-26T16:23:54.934843", "type": "Businesses"}, {"origin": "1010nl.org", "name": "Praktijk voor Fyiotherapie Fysiodeurloo", "url": "http:\/\/www.fysiodeurloo.nl", "country": "NL", "percent_reduction": null, "postcode": "4691 BX", "signed_up_datetime": "2011-02-26T22:14:40.056481", "type": "Businesses"}, {"origin": "1010", "name": "--", "url": null, "country": "FR", "percent_reduction": null, "postcode": "20500", "signed_up_datetime": "2011-02-27T02:34:46.970530", "type": "Universities and colleges"}, {"origin": "brightonandhove1010.org", "name": "South Facing Southern", "url": "http:\/\/www.south-facing.co.uk", "country": "GB", "percent_reduction": null, "postcode": "BN6 8GT", "signed_up_datetime": "2011-02-28T12:36:14.411126", "type": "Businesses"}, {"origin": "1010", "name": "TBLI Conference BV", "url": "http:\/\/www.tbliconference.com", "country": "NL", "percent_reduction": null, "postcode": "1076 CJ", "signed_up_datetime": "2011-02-28T20:17:05.312283", "type": "Businesses"}, {"origin": "1010", "name": "Rural Development Action", "url": null, "country": "GB", "percent_reduction": null, "postcode": "TN25 5BN", "signed_up_datetime": "2011-02-28T20:59:30.631965", "type": "Businesses"}, {"origin": "1010", "name": "SimplyJITH Group", "url": "http:\/\/www.simplyjith.com", "country": "IN", "percent_reduction": null, "postcode": "500020", "signed_up_datetime": "2011-03-01T08:26:25.171246", "type": "Other organisations"}, {"origin": "1010", "name": "Burtt-Jones & Brewer", "url": "http:\/\/www.burtt-jonesandbrewer.com\/", "country": "GB", "percent_reduction": null, "postcode": "BA151RL", "signed_up_datetime": "2011-03-01T08:36:27.348194", "type": "Businesses"}, {"origin": "1010", "name": "Brighthelm Church & Community Centre", "url": "http:\/\/www.brighthelm.org.uk", "country": "GB", "percent_reduction": null, "postcode": "BN1 1YD", "signed_up_datetime": "2011-03-01T10:36:01.731453", "type": "Other organisations"}, {"origin": "1010", "name": "Communaut\u00e9 d'agglom\u00e9ration d'Evry Centre Essonne", "url": "http:\/\/www.agglo-evry.fr", "country": "FR", "percent_reduction": null, "postcode": "91002 Evry Cedex", "signed_up_datetime": "2011-03-01T15:50:26.905399", "type": "Local government"}, {"origin": "1010", "name": "Sunstore", "url": "http:\/\/www.sunstoresolar.co.uk", "country": "GB", "percent_reduction": null, "postcode": "PO5 1EZ", "signed_up_datetime": "2011-03-01T21:43:25.771023", "type": "Businesses"}, {"origin": "1010global.org\/uk\/join", "name": "wave", "url": "http:\/\/www.wave.coop", "country": "GB", "percent_reduction": null, "postcode": "TN34 1HL", "signed_up_datetime": "2011-03-02T10:13:10.467845", "type": "Businesses"}, {"origin": "1010", "name": "Pegonu.com", "url": "http:\/\/www.pegonu.com", "country": "GB", "percent_reduction": null, "postcode": "PO5 1EZ", "signed_up_datetime": "2011-03-02T13:53:33.441333", "type": "Other organisations"}, {"origin": "1010", "name": "Agencia Verde", "url": "http:\/\/www.agenciaverde.org", "country": "CL", "percent_reduction": null, "postcode": "Santiago -R.M.", "signed_up_datetime": "2011-03-02T16:24:56.307861", "type": "Businesses"}, {"origin": "1010finland.fi", "name": "Flo Apps Oy", "url": "http:\/\/www.floapps.com", "country": "FI", "percent_reduction": null, "postcode": "00520", "signed_up_datetime": "2011-03-03T12:45:10.020221", "type": "Businesses"}, {"origin": "1010", "name": "151 Products Ltd", "url": "http:\/\/www.151.co.uk", "country": "GB", "percent_reduction": null, "postcode": "M3 1LG", "signed_up_datetime": "2011-03-04T09:08:08.422199", "type": "Businesses"}, {"origin": "1010finland.fi", "name": "Hub Helsinki", "url": "http:\/\/helsinki.the-hub.net", "country": "FI", "percent_reduction": null, "postcode": "00100 Helsinki", "signed_up_datetime": "2011-03-04T11:59:11.936408", "type": "Businesses"}, {"origin": "1010", "name": "St Mary's Church Eco Team", "url": "http:\/\/meltonmowbray.churchinsight.com\/Groups\/126462\/St_Marys_C\/What_we_do\/Groups\/Eco_Team\/Eco_Team.aspx", "country": "GB", "percent_reduction": null, "postcode": "LE13 1AE", "signed_up_datetime": "2011-03-06T18:35:04.732776", "type": "Faith groups"}, {"origin": "1010", "name": "Club de l'Amiti\u00e9 - ONG D\u00e9veloppement Rural", "url": null, "country": "FR", "percent_reduction": null, "postcode": "00241", "signed_up_datetime": "2011-03-07T11:46:08.450406", "type": "Clubs"}, {"origin": "1010", "name": "Conciencia Ecol\u00f3gica", "url": "http:\/\/www.concienciaecologica.org", "country": "CO", "percent_reduction": null, "postcode": "NA", "signed_up_datetime": "2011-03-07T18:01:05.614817", "type": "Student organisations"}, {"origin": "1010", "name": "Liceo politecnico Andes", "url": null, "country": "CL", "percent_reduction": null, "postcode": "Santiago \/ Metroplitana", "signed_up_datetime": "2011-03-07T23:45:59.705188", "type": "Schools"}, {"origin": "1010", "name": "University of Bristol Conference Office", "url": "http:\/\/www.bris.ac.uk\/conferences-hospitality", "country": "GB", "percent_reduction": null, "postcode": "BS8 1UQ", "signed_up_datetime": "2011-03-08T11:01:59.111440", "type": "Universities and colleges"}, {"origin": "1010", "name": "Secret Garden Party", "url": "http:\/\/www.secretgardenparty.com", "country": "GB", "percent_reduction": null, "postcode": "N79DP", "signed_up_datetime": "2011-03-08T12:09:32.349784", "type": "Businesses"}, {"origin": "1010", "name": "KOP", "url": null, "country": "BD", "percent_reduction": null, "postcode": "6000", "signed_up_datetime": "2011-03-09T21:00:24.429330", "type": "Local government"}, {"origin": "1010", "name": "Helsingin kuvataidelukio", "url": "http:\/\/www.hel.fi\/wps\/portal\/Koulut\/Lukiot\/Kuvatl?WCM_GLOBAL_CONTEXT=\/kuvatl\/fi\/Etusivu", "country": "FI", "percent_reduction": null, "postcode": "00500 Helsinki", "signed_up_datetime": "2011-03-10T14:13:33.422635", "type": "Schools"}, {"origin": "1010", "name": "RVKA TEXTILES", "url": "http:\/\/www.rvkatextiles.com", "country": "IN", "percent_reduction": null, "postcode": "639002", "signed_up_datetime": "2011-03-11T02:35:42.887731", "type": "Health organisations"}, {"origin": "1010", "name": "Polka Theatre", "url": "http:\/\/www.polkatheatre.com", "country": "GB", "percent_reduction": null, "postcode": "SW19 1SB", "signed_up_datetime": "2011-03-12T17:05:46.431345", "type": "Charities"}, {"origin": "1010", "name": "JamHot", "url": "http:\/\/www.thisisjamhot.com", "country": "GB", "percent_reduction": null, "postcode": "G3 8ND", "signed_up_datetime": "2011-03-13T11:44:19.449817", "type": "Businesses"}, {"origin": "1010global.org\/uk\/join", "name": "Inside2Outside", "url": "http:\/\/www.inside2outside.co.uk", "country": "GB", "percent_reduction": null, "postcode": "PE28 9HU", "signed_up_datetime": "2011-03-13T20:14:28.051779", "type": "Businesses"}, {"origin": "http:\/\/noplasticbagday.blogspot.com", "name": "RCOMM", "url": "http:\/\/www.rcomm.org.my", "country": "MY", "percent_reduction": null, "postcode": "48000", "signed_up_datetime": "2011-03-14T05:46:07.754703", "type": "Charities"}, {"origin": "1010finland.fi", "name": "Kuuretki \/ Borneo Colors", "url": "http:\/\/www.borneocolors.fi", "country": "FI", "percent_reduction": null, "postcode": "80110 Joensuu", "signed_up_datetime": "2011-03-14T08:22:05.907653", "type": "Businesses"}, {"origin": "brightonandhove1010.org", "name": "AMA Ltd", "url": "http:\/\/www.amaconsult.co.uk", "country": "GB", "percent_reduction": null, "postcode": "BN14GH", "signed_up_datetime": "2011-03-14T14:24:38.624924", "type": "Businesses"}, {"origin": "1010", "name": "The Gate of Hope", "url": null, "country": "GB", "percent_reduction": null, "postcode": "HA0 9LF", "signed_up_datetime": "2011-03-14T14:48:52.874561", "type": "Charities"}, {"origin": "1010", "name": "Pandora Grafix", "url": null, "country": "DE", "percent_reduction": null, "postcode": "06118", "signed_up_datetime": "2011-03-15T14:12:24.593542", "type": "Other organisations"}, {"origin": "1010", "name": "Airdesert - Unipessoal, Lda", "url": "http:\/\/www.airdesert.com", "country": "PT", "percent_reduction": null, "postcode": "2490-646 Our\u00e9m", "signed_up_datetime": "2011-03-15T15:08:14.764361", "type": "Businesses"}, {"origin": "1010", "name": "Wombling CIC", "url": "http:\/\/www.wombling.org.uk", "country": "GB", "percent_reduction": null, "postcode": "NR8 6FQ", "signed_up_datetime": "2011-03-16T07:22:44.613753", "type": "Businesses"}, {"origin": "1010", "name": "die service manufaktur", "url": "http:\/\/www.dieservicemanufaktur.de", "country": "DE", "percent_reduction": null, "postcode": "81667 M\u00fcnchen", "signed_up_datetime": "2011-03-16T07:56:31.824251", "type": "Businesses"}, {"origin": "1010", "name": "Lillis Conultants", "url": null, "country": "GB", "percent_reduction": null, "postcode": "NR50LZ", "signed_up_datetime": "2011-03-16T14:58:52.660367", "type": "Businesses"}, {"origin": "1010", "name": "Eco Designs", "url": "http:\/\/www.ecodesigns.co.uk", "country": "GB", "percent_reduction": null, "postcode": "WN2 3JW", "signed_up_datetime": "2011-03-16T16:17:38.296018", "type": "Businesses"}, {"origin": "1010global.org\/uk\/join", "name": "Spanish Translation UK", "url": "http:\/\/spanishtranslationuk.com", "country": "GB", "percent_reduction": null, "postcode": "SN2 7QB", "signed_up_datetime": "2011-03-17T01:58:22.957796", "type": "Businesses"}, {"origin": "1010", "name": "National Tertiary Education Union (Victornan Division)", "url": "http:\/\/www.nteu.org.au\/vic", "country": "AU", "percent_reduction": null, "postcode": "3205", "signed_up_datetime": "2011-03-17T03:48:16.496077", "type": "Other organisations"}, {"origin": "1010", "name": "Sunhive Ltd", "url": "http:\/\/www.sunhive.com", "country": "GB", "percent_reduction": null, "postcode": "BN3 2BE", "signed_up_datetime": "2011-03-17T10:17:20.663856", "type": "Businesses"}, {"origin": "1010", "name": "The Mill at Rode", "url": "http:\/\/www.themillatrode.co.uk", "country": "GB", "percent_reduction": null, "postcode": "BA11 6AG", "signed_up_datetime": "2011-03-17T16:06:54.227749", "type": "Businesses"}, {"origin": "1010", "name": "St. John's Primary School", "url": null, "country": "GB", "percent_reduction": null, "postcode": "W130NY", "signed_up_datetime": "2011-03-20T19:15:38.079695", "type": "Schools"}, {"origin": "1010", "name": "omar", "url": "http:\/\/kokokokokokokokokokokoko;o", "country": "EG", "percent_reduction": null, "postcode": "uiplu", "signed_up_datetime": "2011-03-20T19:38:30.999625", "type": "Schools"}, {"origin": "brightonandhove1010.org", "name": "Green Grid UK", "url": null, "country": "GB", "percent_reduction": null, "postcode": "BN3 2PB", "signed_up_datetime": "2011-03-21T09:57:54.649713", "type": "Businesses"}, {"origin": "1010global.org\/uk\/join", "name": "London Communications Agency", "url": "http:\/\/www.londoncommunications.co.uk", "country": "GB", "percent_reduction": null, "postcode": "W1T 4JE", "signed_up_datetime": "2011-03-21T12:11:14.492089", "type": "Businesses"}, {"origin": "1010", "name": "Programa Preservando Para o Futuro - Prefuturo", "url": "http:\/\/www.mma.gov.br", "country": "BR", "percent_reduction": null, "postcode": "62360000", "signed_up_datetime": "2011-03-21T19:52:15.621133", "type": "Other organisations"}, {"origin": "1010", "name": "DABD (uk)", "url": "http:\/\/www.dabd.org.uk", "country": "GB", "percent_reduction": null, "postcode": "RM10 7YP", "signed_up_datetime": "2011-03-22T12:01:42.765384", "type": "Charities"}, {"origin": "1010", "name": "British American Tobacco", "url": "http:\/\/www.bat.com", "country": "GR", "percent_reduction": null, "postcode": "12135", "signed_up_datetime": "2011-03-22T15:43:33.051149", "type": "Businesses"}, {"origin": "1010", "name": "groeneacademie.nl", "url": "http:\/\/www.pierrewind.nl", "country": "NL", "percent_reduction": null, "postcode": "3029 AR Rotterdam", "signed_up_datetime": "2011-03-23T09:39:58.141530", "type": "Other organisations"}, {"origin": "1010", "name": "Gardline Marine Sciences Limited", "url": "http:\/\/www.gardlinemarinesciences.com", "country": "GB", "percent_reduction": null, "postcode": "NR30 3NG", "signed_up_datetime": "2011-03-23T11:02:21.999490", "type": "Businesses"}, {"origin": "1010", "name": "MESPOM", "url": null, "country": "ET", "percent_reduction": null, "postcode": "1000", "signed_up_datetime": "2011-03-23T12:35:54.290953", "type": "Universities and colleges"}, {"origin": "1010", "name": "Our Celebration", "url": "http:\/\/www.ourcelebration.org.uk", "country": "GB", "percent_reduction": null, "postcode": "YO30 6BP", "signed_up_datetime": "2011-03-23T16:02:32.392718", "type": "Charities"}, {"origin": "1010nl.org", "name": "Amsterdam Gay Pride", "url": "http:\/\/www.weareproud.nl", "country": "NL", "percent_reduction": null, "postcode": "1017 BL", "signed_up_datetime": "2011-03-24T12:17:33.183737", "type": "Other organisations"}, {"origin": "1010", "name": "St Martins", "url": "http:\/\/www.stmartinoftours.org.uk", "country": "GB", "percent_reduction": null, "postcode": "N1 2LF", "signed_up_datetime": "2011-03-24T13:20:58.620373", "type": "Other organisations"}, {"origin": "1010", "name": "Pathway to Prospects Ltd", "url": "http:\/\/www.pathwaytoprospects.co.uk", "country": "GB", "percent_reduction": null, "postcode": "M33 4WL", "signed_up_datetime": "2011-03-24T16:27:52.288949", "type": "Businesses"}, {"origin": "1010", "name": "the corner", "url": null, "country": "ES", "percent_reduction": null, "postcode": "08024", "signed_up_datetime": "2011-03-25T10:35:17.457911", "type": "Other organisations"}, {"origin": "brightonandhove1010.org", "name": "ABIR Architects Ltd", "url": "http:\/\/www.abirarchitects.co.uk", "country": "GB", "percent_reduction": null, "postcode": "BN3 2FX", "signed_up_datetime": "2011-03-25T17:33:40.393545", "type": "Businesses"}, {"origin": "1010", "name": "Frootie.co", "url": null, "country": "AU", "percent_reduction": null, "postcode": "2000", "signed_up_datetime": "2011-03-27T10:45:48.114312", "type": "Universities and colleges"}, {"origin": "1010", "name": "DIT", "url": "http:\/\/dit.ie", "country": "IE", "percent_reduction": null, "postcode": "24", "signed_up_datetime": "2011-03-27T18:55:59.304507", "type": "Universities and colleges"}, {"origin": "1010", "name": "Shavington Primary School", "url": null, "country": "GB", "percent_reduction": null, "postcode": "CW2 5BP", "signed_up_datetime": "2011-03-27T19:20:10.077972", "type": "Schools"}, {"origin": "1010", "name": "LDNI", "url": "http:\/\/ldni.co.uk", "country": "GB", "percent_reduction": null, "postcode": "RH4 3HX", "signed_up_datetime": "2011-03-27T21:55:07.194881", "type": "Businesses"}, {"origin": "1010finland.fi", "name": "Puurtilan koulu", "url": null, "country": "FI", "percent_reduction": null, "postcode": "78310 Varkaus", "signed_up_datetime": "2011-03-28T05:45:57.975657", "type": "Schools"}, {"origin": "1010finland.fi", "name": "Viittomakielialan Osuuskunta Via", "url": "http:\/\/www.via-ok.net", "country": "FI", "percent_reduction": null, "postcode": "00520 Helsinki", "signed_up_datetime": "2011-03-28T07:44:57.787666", "type": "Businesses"}, {"origin": "1010global.org\/uk\/join", "name": "TEAM Energy (UK)", "url": "http:\/\/www.teamenergy.com", "country": "GB", "percent_reduction": null, "postcode": "MK14 6LY", "signed_up_datetime": "2011-03-28T09:27:08.720584", "type": "Businesses"}, {"origin": "1010finland.fi", "name": "Gekko Digital Oy", "url": "http:\/\/www.gekkodigital.fi", "country": "FI", "percent_reduction": null, "postcode": "20100", "signed_up_datetime": "2011-03-28T11:20:45.688956", "type": "Businesses"}, {"origin": "1010", "name": "james", "url": "http:\/\/goodchoice.com", "country": "GB", "percent_reduction": null, "postcode": "Postcode", "signed_up_datetime": "2011-03-28T19:57:57.218639", "type": "Businesses"}, {"origin": "1010global.org\/uk\/join", "name": "Yelden Village Hall", "url": "http:\/\/www.yeldenvillagehall.co.uk", "country": "GB", "percent_reduction": null, "postcode": "MK44 1AT", "signed_up_datetime": "2011-03-29T11:16:04.268619", "type": "Charities"}, {"origin": "1010", "name": "Colegiul National de Informatica \"Tudor Vianu\"", "url": "http:\/\/-", "country": "RO", "percent_reduction": null, "postcode": "011356", "signed_up_datetime": "2011-03-29T11:33:46.722858", "type": "Schools"}, {"origin": "1010", "name": "Daisy Vineyards", "url": "http:\/\/superfoodinfos.com\/", "country": "GB", "percent_reduction": null, "postcode": "26101", "signed_up_datetime": "2011-03-29T17:53:22.799978", "type": "Businesses"}, {"origin": "brightonandhove1010.org", "name": "Bid and Borrow", "url": "http:\/\/www.bidandborrow.com", "country": "GB", "percent_reduction": null, "postcode": "BN3 3DH", "signed_up_datetime": "2011-03-30T12:43:21.073394", "type": "Businesses"}, {"origin": "1010", "name": "APASO", "url": "http:\/\/www.apaso.fr\/", "country": "FR", "percent_reduction": null, "postcode": "75014", "signed_up_datetime": "2011-03-31T09:35:06.764253", "type": "Clubs"}, {"origin": "1010finland.fi", "name": "Behnford's Oy", "url": "http:\/\/www.behnfords.fi", "country": "FI", "percent_reduction": null, "postcode": "00100", "signed_up_datetime": "2011-04-01T15:07:47.138127", "type": "Businesses"}, {"origin": "1010", "name": "Royalcress  sa", "url": "http:\/\/www.royalcress.com", "country": "ES", "percent_reduction": null, "postcode": "11401", "signed_up_datetime": "2011-04-04T06:04:58.460767", "type": "Businesses"}, {"origin": "1010global.org\/uk\/join", "name": "J Brand", "url": "http:\/\/www.jbrand.co.uk", "country": "GB", "percent_reduction": null, "postcode": "W1W 8RD", "signed_up_datetime": "2011-04-04T08:15:21.686189", "type": "Businesses"}, {"origin": "1010", "name": "Tudor Vianu High School", "url": null, "country": "GB", "percent_reduction": null, "postcode": "012572", "signed_up_datetime": "2011-04-04T16:55:37.539049", "type": "Schools"}, {"origin": "1010", "name": "AFAB (UK) Ltd", "url": "http:\/\/www.afabinfo.com", "country": "GB", "percent_reduction": null, "postcode": "TQ14 8BW", "signed_up_datetime": "2011-04-04T21:03:13.677067", "type": "Businesses"}, {"origin": "1010", "name": "SIFE Leeds", "url": "http:\/\/www.sifeuk.org\/index.html?mod=universities&id=22", "country": "GB", "percent_reduction": null, "postcode": "LS6 2PB", "signed_up_datetime": "2011-04-05T14:27:11.664569", "type": "Other organisations"}, {"origin": "1010", "name": "St Georges College", "url": null, "country": "GB", "percent_reduction": null, "postcode": "1878", "signed_up_datetime": "2011-04-05T15:16:45.632570", "type": "Schools"}, {"origin": "1010", "name": "portland state university", "url": null, "country": "GB", "percent_reduction": null, "postcode": "97201", "signed_up_datetime": "2011-04-05T23:49:59.073729", "type": "Universities and colleges"}, {"origin": "1010", "name": "Tribal Internet Solutions", "url": "http:\/\/www.tribal.nl", "country": "NL", "percent_reduction": null, "postcode": "5222 AV", "signed_up_datetime": "2011-04-06T12:08:52.246452", "type": "Businesses"}, {"origin": "1010", "name": "Maxishows", "url": "http:\/\/www.maxishows.org", "country": "ES", "percent_reduction": null, "postcode": "08012", "signed_up_datetime": "2011-04-06T16:36:02.190536", "type": "Businesses"}, {"origin": "1010", "name": "azia", "url": "http:\/\/652", "country": "EG", "percent_reduction": null, "postcode": "2469", "signed_up_datetime": "2011-04-06T20:18:07.132675", "type": "Other organisations"}, {"origin": "1010", "name": "Clikyz.Com", "url": "http:\/\/www.clikyz.com", "country": "GB", "percent_reduction": null, "postcode": "CH47 3DH", "signed_up_datetime": "2011-04-07T13:33:02.728254", "type": "Businesses"}, {"origin": "1010", "name": "Hordasken", "url": "http:\/\/www.hordasken.com", "country": "GB", "percent_reduction": null, "postcode": "CH47 3DH", "signed_up_datetime": "2011-04-07T13:35:17.380269", "type": "Other organisations"}, {"origin": "1010", "name": "Guru Nanak Gurdwara, Bedford", "url": null, "country": "GB", "percent_reduction": null, "postcode": "MK40 4PS", "signed_up_datetime": "2011-04-07T15:06:12.683246", "type": "Other organisations"}, {"origin": "1010", "name": "Sisterhood-holdingthingstogether", "url": null, "country": "GB", "percent_reduction": null, "postcode": "SW16 5XD", "signed_up_datetime": "2011-04-07T15:59:36.582318", "type": "Other organisations"}, {"origin": "1010nl.org", "name": "ACTIVE ORGANIZING", "url": "http:\/\/www.activeorganizing.nl", "country": "NL", "percent_reduction": null, "postcode": "3311 VR", "signed_up_datetime": "2011-04-07T18:44:33.739043", "type": "Businesses"}, {"origin": "1010", "name": "ttowntv.com", "url": "http:\/\/www.ttowntv.com", "country": "US", "percent_reduction": null, "postcode": "85748", "signed_up_datetime": "2011-04-09T06:38:36.233300", "type": "Businesses"}, {"origin": "1010", "name": "Rokeby School", "url": "http:\/\/www.rokebyschool.co.uk", "country": "GB", "percent_reduction": null, "postcode": "KT2 7PB", "signed_up_datetime": "2011-04-09T15:43:18.217488", "type": "Schools"}, {"origin": "www.kirtonfarm.co.uk", "name": "Frugal Farmers", "url": "http:\/\/www.frugalfarmers.net", "country": "GB", "percent_reduction": null, "postcode": "TQ4 7DA", "signed_up_datetime": "2011-04-09T17:39:09.513246", "type": "Businesses"}, {"origin": "1010", "name": "Stichting Vrienden van de Gay Krant", "url": "http:\/\/www.GK.nl", "country": "NL", "percent_reduction": null, "postcode": "5680 AA", "signed_up_datetime": "2011-04-10T08:07:31.958999", "type": "Other organisations"}, {"origin": "1010", "name": "System of Thinking", "url": "http:\/\/www.systemofthinking.co.uk", "country": "GB", "percent_reduction": null, "postcode": "CH662UN", "signed_up_datetime": "2011-04-11T15:01:45.415321", "type": "Businesses"}, {"origin": "1010", "name": "friendfund", "url": "http:\/\/www.friendfund.com", "country": "DE", "percent_reduction": null, "postcode": "10407", "signed_up_datetime": "2011-04-11T16:31:12.667365", "type": "Businesses"}, {"origin": "1010", "name": "International Club of St. Gallen", "url": null, "country": "CH", "percent_reduction": null, "postcode": "9000", "signed_up_datetime": "2011-04-12T08:38:11.201992", "type": "Clubs"}, {"origin": "1010", "name": "Energy Software Solutions b.v.", "url": "http:\/\/www.essaver.net", "country": "NL", "percent_reduction": null, "postcode": "6991DK", "signed_up_datetime": "2011-04-12T11:35:48.253329", "type": "Businesses"}, {"origin": "1010nl.org", "name": "prescriptio marketing | reclame | media", "url": "http:\/\/www.prescriptio.nl", "country": "NL", "percent_reduction": null, "postcode": "7512EM", "signed_up_datetime": "2011-04-13T09:52:07.205858", "type": "Businesses"}, {"origin": "1010global.org\/uk\/join", "name": "Whyte & Co", "url": "http:\/\/www.whyte.co.uk", "country": "GB", "percent_reduction": null, "postcode": "BR8 7AG", "signed_up_datetime": "2011-04-13T09:59:36.101919", "type": "Businesses"}, {"origin": "1010", "name": "liceo comercial Nora Vivians Molina", "url": "http:\/\/no", "country": "CL", "percent_reduction": null, "postcode": "santiago", "signed_up_datetime": "2011-04-13T16:08:01.513940", "type": "Schools"}, {"origin": "1010", "name": "to live for you", "url": "http:\/\/www.liveforyou.be", "country": "AQ", "percent_reduction": null, "postcode": "3733", "signed_up_datetime": "2011-04-13T16:20:42.151816", "type": "Health organisations"}, {"origin": "1010", "name": "WDAD Communications Limited", "url": "http:\/\/www.wdad.co.uk", "country": "GB", "percent_reduction": null, "postcode": "EC1N 8TS", "signed_up_datetime": "2011-04-14T10:25:41.394811", "type": "Businesses"}, {"origin": "1010", "name": "Roots Fest 2011", "url": "http:\/\/rootsfest.yolasite.com\/", "country": "GB", "percent_reduction": null, "postcode": "BA2 6BU", "signed_up_datetime": "2011-04-14T12:08:25.560686", "type": "Other organisations"}, {"origin": "1010global.org\/uk\/join", "name": "Oomph Agency Services Ltd", "url": "http:\/\/www.oomphagency.com", "country": "GB", "percent_reduction": null, "postcode": "GL7 1UP", "signed_up_datetime": "2011-04-14T14:11:05.142756", "type": "Businesses"}, {"origin": "1010", "name": "ISIC in Ukraine", "url": "http:\/\/www.isic.org.ua", "country": "UA", "percent_reduction": null, "postcode": "03058", "signed_up_datetime": "2011-04-15T06:09:21.073655", "type": "Student organisations"}, {"origin": "1010finland.fi", "name": "HolyMacaroni", "url": null, "country": "FI", "percent_reduction": null, "postcode": "00010", "signed_up_datetime": "2011-04-15T08:30:19.610533", "type": "Faith groups"}, {"origin": "1010", "name": "v - The National Young Volunteers Service", "url": "http:\/\/www.vinspired.com", "country": "GB", "percent_reduction": null, "postcode": "SW1P 2AF", "signed_up_datetime": "2011-04-15T13:51:33.494308", "type": "Charities"}, {"origin": "1010", "name": "GREEN ATTITUDE Cie", "url": "http:\/\/mp@sc-groupe.com", "country": "FR", "percent_reduction": null, "postcode": "67960", "signed_up_datetime": "2011-04-15T17:21:28.057628", "type": "Businesses"}, {"origin": "1010", "name": "Umbro", "url": null, "country": "GB", "percent_reduction": null, "postcode": "000000", "signed_up_datetime": "2011-04-15T23:42:11.585341", "type": "Businesses"}, {"origin": "1010", "name": "SACRED HEART R.C. PRIMARY SCHOOL", "url": "http:\/\/www.sacred-heart.bolton.sch.uk", "country": "GB", "percent_reduction": null, "postcode": "BL5 3DU", "signed_up_datetime": "2011-04-16T08:17:03.013863", "type": "Schools"}, {"origin": "1010", "name": "www.essaver.net", "url": "http:\/\/www.essaver.net", "country": "NL", "percent_reduction": null, "postcode": "6991DK", "signed_up_datetime": "2011-04-16T22:13:29.343964", "type": "Businesses"}, {"origin": "1010global.org\/uk\/join", "name": "NHTB Consultancy Ltd", "url": "http:\/\/www.nhtb.co.uk", "country": "GB", "percent_reduction": null, "postcode": "EN11 9LA", "signed_up_datetime": "2011-04-18T13:57:39.354878", "type": "Businesses"}, {"origin": "1010", "name": "Isol'centre", "url": "http:\/\/www.isol-centre.fr", "country": "FR", "percent_reduction": null, "postcode": "45000", "signed_up_datetime": "2011-04-18T22:02:07.995453", "type": "Businesses"}, {"origin": "1010", "name": "Adam Gas Services", "url": "http:\/\/www.adamgas.co.uk", "country": "GB", "percent_reduction": null, "postcode": "KA11 3BG", "signed_up_datetime": "2011-04-18T23:16:14.811308", "type": "Businesses"}, {"origin": "1010global.org\/uk\/join", "name": "nas\/clndsv", "url": null, "country": "GB", "percent_reduction": null, "postcode": "ng4 4rg", "signed_up_datetime": "2011-04-19T08:36:48.173434", "type": "Businesses"}, {"origin": "1010finland.fi", "name": "Ekoenergia-merkki", "url": "http:\/\/www.ekoenergia.fi", "country": "FI", "percent_reduction": null, "postcode": "00510 HELSINKI", "signed_up_datetime": "2011-04-19T13:44:21.308773", "type": "Other organisations"}, {"origin": "1010", "name": "compostera.cl", "url": "http:\/\/www.compostera.cl", "country": "CL", "percent_reduction": null, "postcode": "Santiago", "signed_up_datetime": "2011-04-19T22:49:27.378561", "type": "Businesses"}, {"origin": "1010", "name": "http:\/\/www.StopYourEngines.com", "url": "http:\/\/www.StopYourEngines.com", "country": "GB", "percent_reduction": null, "postcode": "Planet Earth", "signed_up_datetime": "2011-04-21T05:21:59.428264", "type": "Other organisations"}, {"origin": "1010", "name": "LegDuCoin", "url": "http:\/\/www.legducoin.fr", "country": "FR", "percent_reduction": null, "postcode": "16000", "signed_up_datetime": "2011-04-21T10:11:30.105392", "type": "Businesses"}, {"origin": "1010", "name": "Health Partners International", "url": null, "country": "GB", "percent_reduction": null, "postcode": "BN7 2PE", "signed_up_datetime": "2011-04-21T14:05:37.324334", "type": "Businesses"}, {"origin": "1010", "name": "Elektronics Europe Ltd", "url": "http:\/\/www.elektronics.co.uk", "country": "GB", "percent_reduction": null, "postcode": "BB12 6HA", "signed_up_datetime": "2011-04-21T14:33:47.699290", "type": "Businesses"}, {"origin": "1010", "name": "The CADISPA Trust", "url": "http:\/\/www.cadispa.org", "country": "GB", "percent_reduction": null, "postcode": "PA1 1JS", "signed_up_datetime": "2011-04-23T22:57:36.233582", "type": "Charities"}, {"origin": "1010global.org\/uk\/join", "name": "Supplies Team", "url": "http:\/\/www.supplies-team.co.uk\/", "country": "GB", "percent_reduction": null, "postcode": "WF6 2TZ", "signed_up_datetime": "2011-04-26T08:09:13.049402", "type": "Businesses"}, {"origin": "1010nl.org", "name": "stichting Valkenhorst (residentiele en ambulante vrouwenopvang)", "url": "http:\/\/www.st-valkenhorst.nl", "country": "NL", "percent_reduction": null, "postcode": "4834 KP", "signed_up_datetime": "2011-04-27T07:19:29.154481", "type": "Charities"}, {"origin": "1010", "name": "Eject Creative Studios", "url": "http:\/\/www.eject.co.uk", "country": "GB", "percent_reduction": null, "postcode": "E3 2GZ", "signed_up_datetime": "2011-04-27T09:10:13.484106", "type": "Businesses"}, {"origin": "1010", "name": "Fairfield Control Systems Ltd", "url": "http:\/\/www.fairgen.co.uk", "country": "GB", "percent_reduction": null, "postcode": "Kirton", "signed_up_datetime": "2011-04-27T10:26:50.211788", "type": "Businesses"}, {"origin": "1010", "name": "Embajada Britanica Santiago", "url": "http:\/\/www.ukinchile.fco.gov.uk", "country": "CL", "percent_reduction": null, "postcode": "Santiago", "signed_up_datetime": "2011-04-27T13:42:43.438005", "type": "Other organisations"}, {"origin": "1010", "name": "Asociaci\u00f3n de Scouts de M\u00e9xico, A.C.", "url": "http\/\/www.asmac.org.mx", "country": "MX", "percent_reduction": null, "postcode": "Canc\u00fan", "signed_up_datetime": "2011-04-28T04:06:02.348774", "type": "Clubs"}, {"origin": "1010", "name": "Lost & found", "url": "http:\/\/www.lostandfoundstore.ca", "country": "CA", "percent_reduction": null, "postcode": "B3K 4B8", "signed_up_datetime": "2011-04-29T01:06:22.365048", "type": "Businesses"}, {"origin": "1010global.org\/uk\/join", "name": "Projects Works", "url": "http:\/\/www.projectsworks.co.uk", "country": "GB", "percent_reduction": null, "postcode": "NE21 4AG", "signed_up_datetime": "2011-04-29T17:11:15.938439", "type": "Businesses"}, {"origin": "1010", "name": "Grupo Natura - Espa\u00f1a", "url": "http:\/\/www.grupo-natura.com", "country": "ES", "percent_reduction": null, "postcode": "E-08750", "signed_up_datetime": "2011-05-01T10:10:15.233986", "type": "Businesses"}, {"origin": "1010", "name": "VEG'en scene", "url": "http:\/\/www.animaliste.fr", "country": "FR", "percent_reduction": null, "postcode": "44290", "signed_up_datetime": "2011-05-01T16:30:50.164940", "type": "Businesses"}, {"origin": "1010", "name": "Fej\u00f8 Permakultur og Omstilling", "url": "http:\/\/fejoepermakultur.wordpress.com", "country": "DK", "percent_reduction": null, "postcode": "4900", "signed_up_datetime": "2011-05-03T07:43:41.916397", "type": "Other organisations"}, {"origin": "1010", "name": "Agregados H&M", "url": "http:\/\/www.grupohym.com", "country": "CR", "percent_reduction": null, "postcode": "Santa Clara", "signed_up_datetime": "2011-05-03T16:43:14.677896", "type": "Businesses"}, {"origin": "1010", "name": "Enta Ticketing Solution", "url": "http:\/\/www.enta.com", "country": "GB", "percent_reduction": null, "postcode": "EC1V 8BB", "signed_up_datetime": "2011-05-04T09:14:06.682656", "type": "Businesses"}, {"origin": "1010", "name": "Ecoguia", "url": "http:\/\/www.ecoguia.cl", "country": "CL", "percent_reduction": null, "postcode": "Santiago", "signed_up_datetime": "2011-05-04T13:08:27.185573", "type": "Businesses"}, {"origin": "1010", "name": "Organization for Youth & Development", "url": "http:\/\/www.oydworld.org", "country": "PK", "percent_reduction": null, "postcode": "25000", "signed_up_datetime": "2011-05-04T17:09:36.149499", "type": "Other organisations"}, {"origin": "1010", "name": "Vauxhall Practice", "url": "http:\/\/www.vauxhallpractice.co.uk", "country": "GB", "percent_reduction": null, "postcode": "NP16 5PZ", "signed_up_datetime": "2011-05-05T08:05:30.320551", "type": "Health organisations"}, {"origin": "1010global.org\/uk\/join", "name": "BIMS", "url": "http:\/\/www.bimsedu.com", "country": "GB", "percent_reduction": null, "postcode": "1212", "signed_up_datetime": "2011-05-06T13:12:29.153932", "type": "Other organisations"}, {"origin": "1010", "name": "Africa Youth Trust", "url": "http:\/\/www.africayouthtrust.org", "country": "KE", "percent_reduction": null, "postcode": "00200", "signed_up_datetime": "2011-05-06T19:40:05.861797", "type": "Businesses"}, {"origin": "www.withoutahitch.co.uk", "name": "How Can We Help You", "url": "http:\/\/www.hcwhy.co.uk", "country": "GB", "percent_reduction": null, "postcode": "KT12 5JD", "signed_up_datetime": "2011-05-08T08:59:58.727301", "type": "Businesses"}, {"origin": "1010", "name": "markku.suominen@kymp.net", "url": null, "country": "AS", "percent_reduction": null, "postcode": "6445", "signed_up_datetime": "2011-05-08T15:59:01.075428", "type": "Businesses"}, {"origin": "1010", "name": "Centrum Maatschappelijke Ontwikkeling Groningen", "url": "http:\/\/www.cmogroningen.nl", "country": "NL", "percent_reduction": null, "postcode": "9704 CG", "signed_up_datetime": "2011-05-09T11:16:22.701738", "type": "Businesses"}, {"origin": "1010nl.org", "name": "TSM Business School", "url": "http:\/\/www.tsm.nl", "country": "NL", "percent_reduction": null, "postcode": "7521AG", "signed_up_datetime": "2011-05-09T15:06:29.575796", "type": "Schools"}, {"origin": "1010", "name": "Edinburgh University Gymnastics Club", "url": "http:\/\/gymnastics.eusu.ed.ac.uk\/", "country": "GB", "percent_reduction": null, "postcode": "EH8 9TJ", "signed_up_datetime": "2011-05-09T15:35:20.896099", "type": "Clubs"}, {"origin": "1010", "name": "Crown Inn Marston Montgomery", "url": "http:\/\/www.thecrowninnderbyshire.co.uk", "country": "GB", "percent_reduction": null, "postcode": "DE6 2FF", "signed_up_datetime": "2011-05-10T12:13:29.600445", "type": "Businesses"}, {"origin": "1010", "name": "Howell Southard Grange", "url": null, "country": "US", "percent_reduction": null, "postcode": "07731", "signed_up_datetime": "2011-05-10T12:47:29.968115", "type": "Local government"}, {"origin": "1010", "name": "Teiya", "url": "http:\/\/www.google.com\/", "country": "NZ", "percent_reduction": null, "postcode": "Postcode", "signed_up_datetime": "2011-05-11T06:27:25.031073", "type": "Health organisations"}, {"origin": "1010", "name": "Alex", "url": "http:\/\/www.bing.com\/", "country": "VE", "percent_reduction": null, "postcode": "Postcode", "signed_up_datetime": "2011-05-11T07:34:19.926051", "type": "Faith groups"}, {"origin": "1010", "name": "Walter Bailey Sculture Ltd", "url": "http:\/\/www.walterbailey.co.uk", "country": "GB", "percent_reduction": null, "postcode": "BN25 2UH", "signed_up_datetime": "2011-05-11T11:00:41.487275", "type": "Other organisations"}, {"origin": "1010", "name": "Bourbon Immobilier IR", "url": "http:\/\/www.bourbon-immobilier.com", "country": "FR", "percent_reduction": null, "postcode": "03000 MOULINS", "signed_up_datetime": "2011-05-11T15:34:42.436197", "type": "Businesses"}, {"origin": "1010", "name": "Susy", "url": "http:\/\/www.yahoo.com\/", "country": "GB", "percent_reduction": null, "postcode": "Postcode", "signed_up_datetime": "2011-05-11T19:50:16.788073", "type": "Student organisations"}, {"origin": "1010", "name": "Roselle Events", "url": "http:\/\/www.roselleevents.co.uk", "country": "GB", "percent_reduction": null, "postcode": "EH4 2BN", "signed_up_datetime": "2011-05-12T10:51:30.798321", "type": "Businesses"}, {"origin": "1010", "name": "Center for Work Life Balance-cbaf.dk", "url": "http::\/\/www.cbaf.dk", "country": "DK", "percent_reduction": null, "postcode": "2980", "signed_up_datetime": "2011-05-13T14:24:47.021286", "type": "Businesses"}, {"origin": "brightonandhove1010.org", "name": "Sam's Of Brighton", "url": "http:\/\/www.samsofbrighton.co.uk", "country": "GB", "percent_reduction": null, "postcode": "BN2 1HA", "signed_up_datetime": "2011-05-16T11:42:52.928413", "type": "Businesses"}, {"origin": "1010", "name": "BUi, Beterschap in Uitvoering", "url": null, "country": "NL", "percent_reduction": null, "postcode": "2806 CL", "signed_up_datetime": "2011-05-16T13:02:19.682383", "type": "Businesses"}, {"origin": "1010", "name": "Les Nomades Alg\u00e9riens, Oran", "url": "http:\/\/www.nomades-algeriens.com", "country": "FR", "percent_reduction": null, "postcode": "31000", "signed_up_datetime": "2011-05-17T21:28:20.557329", "type": "Clubs"}, {"origin": "1010", "name": "Royal College of Nursing", "url": "http:\/\/www.rcn.org.uk", "country": "GB", "percent_reduction": null, "postcode": "W1G 0RN", "signed_up_datetime": "2011-05-18T08:56:48.541958", "type": "Health organisations"}, {"origin": "http:\/\/www.britishgas.co.uk", "name": "Orchid IT", "url": "http:\/\/www.orchidit.com", "country": "GB", "percent_reduction": null, "postcode": "DE24 8GX", "signed_up_datetime": "2011-05-18T10:54:03.661180", "type": "Businesses"}, {"origin": "1010", "name": "CLARE", "url": null, "country": "GB", "percent_reduction": null, "postcode": "jfdklj", "signed_up_datetime": "2011-05-18T12:39:57.720756", "type": "Businesses"}, {"origin": "1010global.org\/uk\/join", "name": "Community and Voluntary Service", "url": "http:\/\/www.yourcvs.org", "country": "GB", "percent_reduction": null, "postcode": "MK40 2AA", "signed_up_datetime": "2011-05-18T14:42:28.449279", "type": "Charities"}, {"origin": "1010", "name": "Instituto Superior de Engenharia de Lisboa", "url": "http:\/\/www.isel.pt", "country": "PT", "percent_reduction": null, "postcode": "1959-007 Lisboa", "signed_up_datetime": "2011-05-18T15:59:06.636497", "type": "Universities and colleges"}, {"origin": "1010", "name": "Clean for Life- CFLPERU", "url": "http:\/\/www.cflperu.com", "country": "PE", "percent_reduction": null, "postcode": "Lima 18", "signed_up_datetime": "2011-05-18T21:20:01.726537", "type": "Businesses"}, {"origin": "1010global.org\/uk\/join", "name": "Victorian Plumbing", "url": "http:\/\/www.victorianplumbing.co.uk", "country": "GB", "percent_reduction": null, "postcode": "L37 8EG", "signed_up_datetime": "2011-05-19T09:04:07.385881", "type": "Businesses"}, {"origin": "1010global.org\/uk\/join", "name": "The USURA Group of Companies", "url": "http:\/\/www.theusuragroup.com", "country": "GB", "percent_reduction": null, "postcode": "WF13 3LG", "signed_up_datetime": "2011-05-19T13:16:14.982007", "type": "Businesses"}, {"origin": "1010", "name": "La C\u00e1mara Argentino Danesa de Industria y Comercio", "url": "http:\/\/www.camaradanesa.org.ar", "country": "AR", "percent_reduction": null, "postcode": "C1001AAS", "signed_up_datetime": "2011-05-19T19:11:36.482381", "type": "Other organisations"}, {"origin": "1010", "name": "Center for Participatory Research and Development", "url": "http:\/\/www.prdibd.net", "country": "GB", "percent_reduction": null, "postcode": "1212", "signed_up_datetime": "2011-05-20T11:59:27.275583", "type": "Other organisations"}]}